unstructured_haystack/__about__.py
unstructured_haystack/__init__.py
unstructured_haystack/discord.py
unstructured_haystack/github.py
unstructured_haystack/google_drive.py
unstructured_haystack/unstuctured_haystack.py
unstructured_haystack-0.0.7.dist-info/METADATA
unstructured_haystack-0.0.7.dist-info/WHEEL
unstructured_haystack-0.0.7.dist-info/licenses/LICENSE.txt
unstructured_haystack-0.0.7.dist-info/RECORD
