Metadata-Version: 2.1
Name: unstructured-haystack
Version: 0.0.7
Project-URL: Documentation, https://github.com/unknown/unstructured-haystack#readme
Project-URL: Issues, https://github.com/unknown/unstructured-haystack/issues
Project-URL: Source, https://github.com/unknown/unstructured-haystack
Author-email: Tuana Celik <tuana.celik@deepset.ai>
License-Expression: MIT
License-File: LICENSE.txt
Classifier: Development Status :: 4 - Beta
Classifier: Programming Language :: Python
Classifier: Programming Language :: Python :: 3.7
Classifier: Programming Language :: Python :: 3.8
Classifier: Programming Language :: Python :: 3.9
Classifier: Programming Language :: Python :: 3.10
Classifier: Programming Language :: Python :: 3.11
Classifier: Programming Language :: Python :: Implementation :: CPython
Classifier: Programming Language :: Python :: Implementation :: PyPy
Requires-Python: >=3.7
Requires-Dist: haystack-ai
Requires-Dist: safetensors==0.3.3.post1
Requires-Dist: unstructured-inference
Requires-Dist: unstructured[discord,github,google-drive]
